baseclasses/__init__.py
baseclasses/problems/FluidProperties.py
baseclasses/problems/ICAOAtmosphere.py
baseclasses/problems/__init__.py
baseclasses/problems/pyAeroStruct_problem.py
baseclasses/problems/pyAero_problem.py
baseclasses/problems/pyEngine_problem.py
baseclasses/problems/pyFieldPerformance_problem.py
baseclasses/problems/pyLG_problem.py
baseclasses/problems/pyMission_problem.py
baseclasses/problems/pyStruct_problem.py
baseclasses/problems/pyTransi_problem.py
baseclasses/problems/pyWeight_problem.py
baseclasses/solvers/BaseSolver.py
baseclasses/solvers/__init__.py
baseclasses/solvers/pyAero_solver.py
baseclasses/testing/__init__.py
baseclasses/testing/assertions.py
baseclasses/testing/decorators.py
baseclasses/testing/pyRegTest.py
baseclasses/utils/__init__.py
baseclasses/utils/containers.py
baseclasses/utils/error.py
baseclasses/utils/fileIO.py
baseclasses/utils/solverHistory.py
baseclasses/utils/utils.py
mdolab_baseclasses-1.8.4.dist-info/LICENSE.md
mdolab_baseclasses-1.8.4.dist-info/METADATA
mdolab_baseclasses-1.8.4.dist-info/WHEEL
mdolab_baseclasses-1.8.4.dist-info/top_level.txt
mdolab_baseclasses-1.8.4.dist-info/RECORD
