Metadata-Version: 2.1
Name: mdolab-baseclasses
Version: 1.8.4
Summary: base classes that are used together with the rest of MDO Lab tools.
Home-page: https://github.com/mdolab/baseclasses
Author: 
Author-email: 
License: Apache License Version 2.0
Platform: UNKNOWN
Classifier: Operating System :: OS Independent
Classifier: Topic :: Scientific/Engineering
Classifier: Programming Language :: Python
Requires-Dist: numpy>=1.21
Provides-Extra: docs
Requires-Dist: sphinx-mdolab-theme; extra == "docs"
Provides-Extra: testing
Requires-Dist: testflo; extra == "testing"
Requires-Dist: parameterized; extra == "testing"
